{
    "key": "group_67b4675156c6f",
    "title": "Brief Description",
    "fields": [
        {
            "key": "field_67b46b87d8624",
            "label": "Left Column",
            "name": "",
            "aria-label": "",
            "type": "tab",
            "instructions": "",
            "required": 0,
            "conditional_logic": 0,
            "wrapper": {
                "width": "",
                "class": "",
                "id": ""
            },
            "placement": "top",
            "endpoint": 0
        },
        {
            "key": "field_67b4675151ed8",
            "label": "Title",
            "name": "title",
            "aria-label": "",
            "type": "text",
            "instructions": "",
            "required": 0,
            "conditional_logic": 0,
            "wrapper": {
                "width": "",
                "class": "",
                "id": ""
            },
            "default_value": "",
            "maxlength": "",
            "placeholder": "",
            "prepend": "",
            "append": ""
        },
        {
            "key": "field_67b4678051ed9",
            "label": "Text",
            "name": "text",
            "aria-label": "",
            "type": "text",
            "instructions": "",
            "required": 0,
            "conditional_logic": 0,
            "wrapper": {
                "width": "",
                "class": "",
                "id": ""
            },
            "default_value": "",
            "maxlength": "",
            "placeholder": "",
            "prepend": "",
            "append": ""
        },
        {
            "key": "field_67b46b1c51eda",
            "label": "List",
            "name": "list",
            "aria-label": "",
            "type": "group",
            "instructions": "",
            "required": 0,
            "conditional_logic": 0,
            "wrapper": {
                "width": "",
                "class": "",
                "id": ""
            },
            "layout": "block",
            "sub_fields": [
                {
                    "key": "field_67b46b2b51edb",
                    "label": "Title",
                    "name": "title",
                    "aria-label": "",
                    "type": "text",
                    "instructions": "",
                    "required": 0,
                    "conditional_logic": 0,
                    "wrapper": {
                        "width": "",
                        "class": "",
                        "id": ""
                    },
                    "default_value": "",
                    "maxlength": "",
                    "placeholder": "",
                    "prepend": "",
                    "append": ""
                },
                {
                    "key": "field_67b46b3c51edc",
                    "label": "Items",
                    "name": "items",
                    "aria-label": "",
                    "type": "repeater",
                    "instructions": "",
                    "required": 0,
                    "conditional_logic": 0,
                    "wrapper": {
                        "width": "",
                        "class": "",
                        "id": ""
                    },
                    "layout": "block",
                    "pagination": 0,
                    "min": 0,
                    "max": 0,
                    "collapsed": "",
                    "button_label": "Add Row",
                    "rows_per_page": 20,
                    "sub_fields": [
                        {
                            "key": "field_67c084bf3f78b",
                            "label": "Icon",
                            "name": "icon_type",
                            "aria-label": "",
                            "type": "radio",
                            "instructions": "",
                            "required": 0,
                            "conditional_logic": 0,
                            "wrapper": {
                                "width": "20",
                                "class": "",
                                "id": ""
                            },
                            "choices": {
                                "default": "Default",
                                "custom": "Custom"
                            },
                            "default_value": "default",
                            "return_format": "value",
                            "allow_null": 0,
                            "other_choice": 0,
                            "layout": "horizontal",
                            "save_other_choice": 0,
                            "parent_repeater": "field_67b46b3c51edc"
                        },
                        {
                            "key": "field_67c084993f78a",
                            "label": "File",
                            "name": "icon",
                            "aria-label": "",
                            "type": "image",
                            "instructions": "",
                            "required": 0,
                            "conditional_logic": [
                                [
                                    {
                                        "field": "field_67c084bf3f78b",
                                        "operator": "==",
                                        "value": "custom"
                                    }
                                ]
                            ],
                            "wrapper": {
                                "width": "80",
                                "class": "",
                                "id": ""
                            },
                            "return_format": "url",
                            "library": "all",
                            "min_width": "",
                            "min_height": "",
                            "min_size": "",
                            "max_width": "",
                            "max_height": "",
                            "max_size": "",
                            "mime_types": "",
                            "preview_size": "thumbnail",
                            "parent_repeater": "field_67b46b3c51edc"
                        },
                        {
                            "key": "field_67b46b5a51edd",
                            "label": "Text",
                            "name": "text",
                            "aria-label": "",
                            "type": "text",
                            "instructions": "",
                            "required": 0,
                            "conditional_logic": 0,
                            "wrapper": {
                                "width": "",
                                "class": "",
                                "id": ""
                            },
                            "default_value": "",
                            "maxlength": "",
                            "placeholder": "",
                            "prepend": "",
                            "append": "",
                            "parent_repeater": "field_67b46b3c51edc"
                        }
                    ]
                }
            ]
        },
        {
            "key": "field_67b46b96d8625",
            "label": "Right Column",
            "name": "",
            "aria-label": "",
            "type": "tab",
            "instructions": "",
            "required": 0,
            "conditional_logic": 0,
            "wrapper": {
                "width": "",
                "class": "",
                "id": ""
            },
            "placement": "top",
            "endpoint": 0
        },
        {
            "key": "field_67b46ba1d8626",
            "label": "Subtitle",
            "name": "rc_subtitle",
            "aria-label": "",
            "type": "text",
            "instructions": "",
            "required": 0,
            "conditional_logic": 0,
            "wrapper": {
                "width": "",
                "class": "",
                "id": ""
            },
            "default_value": "",
            "maxlength": "",
            "placeholder": "",
            "prepend": "",
            "append": ""
        },
        {
            "key": "field_67b46d07e33fe",
            "label": "Text",
            "name": "rc_text",
            "aria-label": "",
            "type": "text",
            "instructions": "",
            "required": 0,
            "conditional_logic": 0,
            "wrapper": {
                "width": "",
                "class": "",
                "id": ""
            },
            "default_value": "",
            "maxlength": "",
            "placeholder": "",
            "prepend": "",
            "append": ""
        },
        {
            "key": "field_67b46badd8627",
            "label": "Speakers",
            "name": "rc_speakers",
            "aria-label": "",
            "type": "relationship",
            "instructions": "",
            "required": 0,
            "conditional_logic": 0,
            "wrapper": {
                "width": "",
                "class": "",
                "id": ""
            },
            "post_type": [
                "app_team",
                "app_speaker"
            ],
            "post_status": [
                "publish"
            ],
            "taxonomy": "",
            "filters": [
                "search",
                "post_type"
            ],
            "return_format": "object",
            "min": "",
            "max": "",
            "elements": [
                "featured_image"
            ],
            "bidirectional": 0,
            "bidirectional_target": []
        }
    ],
    "location": [
        [
            {
                "param": "block",
                "operator": "==",
                "value": "acf\/brief-description"
            }
        ]
    ],
    "menu_order": 0,
    "position": "normal",
    "style": "default",
    "label_placement": "top",
    "instruction_placement": "label",
    "hide_on_screen": "",
    "active": true,
    "description": "",
    "show_in_rest": 0,
    "modified": 1740670191
}
